haruka_bot/__init__.py
haruka_bot/__main__.py
haruka_bot/cli/__init__.py
haruka_bot/cli/bot.py
haruka_bot/cli/utils.py
haruka_bot/config.py
haruka_bot/database/__init__.py
haruka_bot/database/db.py
haruka_bot/database/models.py
haruka_bot/libs/__init__.py
haruka_bot/libs/dynamic/__init__.py
haruka_bot/libs/dynamic/card.py
haruka_bot/libs/dynamic/desc.py
haruka_bot/libs/dynamic/display.py
haruka_bot/libs/dynamic/user_profile.py
haruka_bot/plugins/__init__.py
haruka_bot/plugins/at/__init__.py
haruka_bot/plugins/at/at_off.py
haruka_bot/plugins/at/at_on.py
haruka_bot/plugins/auto_agree.py
haruka_bot/plugins/auto_delete.py
haruka_bot/plugins/dynamic/__init__.py
haruka_bot/plugins/dynamic/dynamic_off.py
haruka_bot/plugins/dynamic/dynamic_on.py
haruka_bot/plugins/help.py
haruka_bot/plugins/live/__init__.py
haruka_bot/plugins/live/live_now.py
haruka_bot/plugins/live/live_off.py
haruka_bot/plugins/live/live_on.py
haruka_bot/plugins/permission/__init__.py
haruka_bot/plugins/permission/permission_off.py
haruka_bot/plugins/permission/permission_on.py
haruka_bot/plugins/pusher/__init__.py
haruka_bot/plugins/pusher/dynamic_pusher.py
haruka_bot/plugins/pusher/live_pusher.py
haruka_bot/plugins/sub/__init__.py
haruka_bot/plugins/sub/add_sub.py
haruka_bot/plugins/sub/delete_sub.py
haruka_bot/plugins/sub/sub_list.py
haruka_bot/utils/__init__.py
haruka_bot/utils/browser.py
haruka_bot/utils/fonts_provider.py
haruka_bot/utils/mobile.js
haruka_bot/version.py
haruka_bot-1.6.0.post5.dist-info/entry_points.txt
haruka_bot-1.6.0.post5.dist-info/WHEEL
haruka_bot-1.6.0.post5.dist-info/METADATA
haruka_bot-1.6.0.post5.dist-info/licenses/LICENSE
haruka_bot-1.6.0.post5.dist-info/RECORD
