Metadata-Version: 2.1
Name: haruka-bot
Version: 1.6.0post5
Summary: Push dynamics and live informations from bilibili to QQ. Based on nonebot2.
License: AGPL-3.0-or-later
Keywords: nonebot,nonebot2,qqbot,bilibili,bot
Author-email: SK-415 <2967923486@qq.com>
Requires-Python: >=3.8,<4.0
Requires-Dist: aunly-captcha-solver>=0.1
Requires-Dist: bilireq>=0.2.6
Requires-Dist: click>=8.1.3
Requires-Dist: httpx>=0.24.1
Requires-Dist: msvc-runtime>=14.34.31931; sys_platform == "win32"
Requires-Dist: nonebot-adapter-onebot>=2.2.3
Requires-Dist: nonebot-plugin-apscheduler>=0.3.0
Requires-Dist: nonebot-plugin-guild-patch>=0.2.3
Requires-Dist: nonebot2[fastapi]>=2.0.0
Requires-Dist: packaging>=23.1
Requires-Dist: playwright>=1.35.0
Requires-Dist: pydantic<=2.0,>=1.10.9
Requires-Dist: python-dotenv>=1.0.0
Requires-Dist: tortoise-orm[asyncpg]>=0.19.3
Project-URL: documentation, https://github.com/SK-415/HarukaBot#readme
Project-URL: homepage, https://github.com/SK-415/HarukaBot
Project-URL: repository, https://github.com/SK-415/HarukaBot/tree/master/src/plugins/haruka_bot
